socket_request/__init__.py
socket_request/__main__.py
socket_request/__version__.py
socket_request/control_chain_cli.py
socket_request/core/connect_sock.py
socket_request/core/control_chain.py
socket_request/core/docker_sock.py
socket_request/utils/data.py
socket_request/utils/utils.py
socket_request-1.1.27.dist-info/METADATA
socket_request-1.1.27.dist-info/WHEEL
socket_request-1.1.27.dist-info/entry_points.txt
socket_request-1.1.27.dist-info/top_level.txt
socket_request-1.1.27.dist-info/RECORD
