Metadata-Version: 2.1
Name: socket_request
Version: 1.1.27
Summary: socket_request is building and parsing HTTP requests with UNIX domain sockets.
Home-page: https://github.com/jinwoo-j/socket_request
Author: Jinwoo Jeong
Author-email: jinwoo@parametacorp.com
License: MIT
Classifier: Programming Language :: Python :: 3
Classifier: License :: OSI Approved :: MIT License
Classifier: Operating System :: OS Independent
Requires-Python: >=3.7
Requires-Dist: halo (>=0.0.31)
Requires-Dist: pawnlib (>=2.0.17)
